{
  "index": "2",
  "name": "A Quatryl Scorned",
  "flowChartGroup": "itu",
  "edition": "itu",
  "unlocks": [
    "3"
  ],
  "rewards": {
    "gold": 15,
    "items": [
      "33-gh",
      "33-gh"
    ]
  },
  "monsters": [
    "ancient-artililery",
    "bandit-archer",
    "bandit-guard"
  ],
  "objectives": [
    {
      "name": "Door 2",
      "health": "10",
      "marker": "2"
    }
  ],
  "rules": [
    {
      "round": "true",
      "always": true,
      "once": true,
      "figures": [
        {
          "identifier": {
            "type": "monster",
            "edition": "itu",
            "name": "barty-half-ear"
          },
          "type": "killed"
        }
      ],
      "finish": "won"
    }
  ],
  "rooms": [
    {
      "roomNumber": 1,
      "ref": "i1a",
      "initial": true,
      "rooms": [
        2
      ],
      "monster": [
        {
          "name": "ancient-artillery",
          "player2": "normal",
          "player3": "normal",
          "player4": "elite"
        },
        {
          "name": "ancient-artillery",
          "player2": "normal",
          "player3": "elite",
          "player4": "elite"
        },
        {
          "name": "bandit-guard",
          "type": "elite"
        },
        {
          "name": "bandit-guard",
          "player2": "normal",
          "player3": "normal",
          "player4": "elite"
        },
        {
          "name": "bandit-guard",
          "player3": "normal",
          "player4": "normal"
        }
      ]
    },
    {
      "roomNumber": 2,
      "ref": "i2b",
      "rooms": [
        3
      ],
      "monster": [
        {
          "name": "ancient-artillery",
          "player2": "normal",
          "player3": "normal",
          "player4": "elite"
        },
        {
          "name": "ancient-artillery",
          "player2": "normal",
          "player3": "elite",
          "player4": "elite"
        },
        {
          "name": "bandit-archer",
          "type": "normal"
        },
        {
          "name": "bandit-archer",
          "player2": "normal",
          "player3": "elite",
          "player4": "elite"
        },
        {
          "name": "bandit-guard",
          "type": "normal"
        },
        {
          "name": "bandit-guard",
          "player4": "normal"
        }
      ]
    },
    {
      "roomNumber": 3,
      "ref": "a1b",
      "rooms": [
        4
      ],
      "monster": [
        {
          "name": "bandit-archer",
          "player2": "normal",
          "player3": "elite",
          "player4": "elite"
        },
        {
          "name": "bandit-archer",
          "player2": "normal",
          "player3": "elite",
          "player4": "elite"
        }
      ],
      "objectives": [
        1
      ]
    },
    {
      "roomNumber": 4,
      "ref": "b2a",
      "monster": [
        {
          "name": "barty-half-ear",
          "type": "boss"
        }
      ]
    }
  ]
}